{
	"whipper":
	{
		"stackExperience" :
		[
			{
				"bonus" :
				{
					"subtype" : 0,
					"type" : "PRIMARY_SKILL"
				},
				"values" : [ 0, 1, 1, 1, 1, 2, 2, 2, 2, 3 ]
			},	
			{
				"bonus" :
				{
					"subtype" : 1,
					"type" : "PRIMARY_SKILL"
				},
				"values" : [ 1, 1, 1, 1, 2, 2, 2, 2, 3, 3 ]
			},
			{
				"bonus" :
				{
					"subtype" : 2,
					"type" : "CREATURE_DAMAGE"
				},
				"values" : [ 0, 0, 1, 1, 1, 1, 2, 2, 2, 2 ]
			},
			{
				"bonus" :
				{
					"subtype" : 1,
					"type" : "CREATURE_DAMAGE"
				},
				"values" : [ 0, 0, 0, 1, 1, 1, 1, 2, 2, 2 ]
			},
			{
				"bonus" :
				{
					"valueType" : "PERCENT_TO_BASE",
					"type" : "STACK_HEALTH"
				},
				"values" : [ 5, 10, 15, 20, 25, 30, 35, 40, 45, 50 ]
			},
			{
				"bonus" :
				{
					"type" : "STACKS_SPEED"
				},
				"values" : [ 0, 0, 0, 0, 1, 1, 1, 1, 1, 2 ]
			},
			{
				"bonus" :
				{
					"type" : "ADDITIONAL_RETALIATION"
				},
				"values" : [ 0, 0, 0, 1, 1, 1, 1, 1, 1, 2 ]
			}				
		]	
	},

	"overseer":
	{
		"stackExperience" :
		[
			{
				"bonus" :
				{
					"subtype" : 0,
					"type" : "PRIMARY_SKILL"
				},
				"values" : [ 0, 1, 1, 1, 1, 2, 2, 2, 2, 3 ]
			},	
			{
				"bonus" :
				{
					"subtype" : 1,
					"type" : "PRIMARY_SKILL"
				},
				"values" : [ 1, 1, 1, 1, 2, 2, 2, 2, 3, 3 ]
			},
			{
				"bonus" :
				{
					"subtype" : 2,
					"type" : "CREATURE_DAMAGE"
				},
				"values" : [ 0, 0, 1, 1, 1, 1, 2, 2, 2, 2 ]
			},
			{
				"bonus" :
				{
					"subtype" : 1,
					"type" : "CREATURE_DAMAGE"
				},
				"values" : [ 0, 0, 0, 1, 1, 1, 1, 2, 2, 2 ]
			},
			{
				"bonus" :
				{
					"valueType" : "PERCENT_TO_BASE",
					"type" : "STACK_HEALTH"
				},
				"values" : [ 5, 10, 15, 20, 25, 30, 35, 40, 45, 50 ]
			},
			{
				"bonus" :
				{
					"type" : "STACKS_SPEED"
				},
				"values" : [ 0, 0, 0, 0, 1, 1, 1, 1, 1, 2 ]
			},
			{
				"bonus" :
				{
					"type" : "ADDITIONAL_RETALIATION"
				},
				"values" : [ 0, 0, 0, 1, 1, 1, 1, 1, 1, 2 ]
			},
			{
				"bonus" :
				{
					"type" : "CHARGE_IMMUNITY"
				},
				"values" : [ false, false, true, true, true, true, true, true, true, true ]
			}			
		]	
	},
	
	"wadjet":
	{
		"stackExperience" :
		[
			{
				"bonus" :
				{
					"subtype" : 0,
					"type" : "PRIMARY_SKILL"
				},
				"values" : [ 0, 1, 1, 2, 2, 2, 3, 3, 3, 4 ]
			},	
			{
				"bonus" :
				{
					"subtype" : 1,
					"type" : "PRIMARY_SKILL"
				},
				"values" : [ 1, 1, 1, 2, 2, 3, 3, 3, 4, 4 ]
			},
			{
				"bonus" :
				{
					"subtype" : 2,
					"type" : "CREATURE_DAMAGE"
				},
				"values" : [ 0, 1, 1, 1, 2, 2, 2, 3, 3, 4 ]
			},
			{
				"bonus" :
				{
					"subtype" : 1,
					"type" : "CREATURE_DAMAGE"
				},
				"values" : [ 0, 0, 1, 1, 1, 2, 2, 3, 3, 3 ]
			},
			{
				"bonus" :
				{
					"valueType" : "PERCENT_TO_BASE",
					"type" : "STACK_HEALTH"
				},
				"values" : [ 5, 10, 15, 20, 25, 30, 35, 40, 45, 50 ]
			},
			{
				"bonus" :
				{
					"type" : "STACKS_SPEED"
				},
				"values" : [ 0, 0, 0, 1, 1, 1, 1, 1, 1, 2 ]
			},
			{
				"bonus" :
				{
					"type" : "HEALER"
				},
				"values" : [ false, false, false, false, true, true, true, true, true, true ]
			}			
		]	
	},

	"venomousWadjet":
	{
		"stackExperience" :
		[
			{
				"bonus" :
				{
					"subtype" : 0,
					"type" : "PRIMARY_SKILL"
				},
				"values" : [ 0, 1, 1, 2, 2, 2, 3, 3, 3, 4 ]
			},	
			{
				"bonus" :
				{
					"subtype" : 1,
					"type" : "PRIMARY_SKILL"
				},
				"values" : [ 1, 1, 1, 2, 2, 3, 3, 3, 4, 4 ]
			},
			{
				"bonus" :
				{
					"subtype" : 2,
					"type" : "CREATURE_DAMAGE"
				},
				"values" : [ 0, 1, 1, 1, 2, 2, 2, 3, 3, 4 ]
			},
			{
				"bonus" :
				{
					"subtype" : 1,
					"type" : "CREATURE_DAMAGE"
				},
				"values" : [ 0, 0, 1, 1, 1, 2, 2, 3, 3, 3 ]
			},
			{
				"bonus" :
				{
					"valueType" : "PERCENT_TO_BASE",
					"type" : "STACK_HEALTH"
				},
				"values" : [ 5, 10, 15, 20, 25, 30, 35, 40, 45, 50 ]
			},
			{
				"bonus" :
				{
					"type" : "STACKS_SPEED"
				},
				"values" : [ 0, 0, 0, 1, 1, 1, 1, 1, 1, 2 ]
			},
			{
				"bonus" :
				{
					"type" : "SPELL_AFTER_ATTACK",
					"subtype" : 71, //"spell.poison",
					"addInfo" : [ 1, 2 ]
				},
				"values" : [ 5, 10, 15, 20, 25, 30, 35, 40, 45, 50 ]
			}			
		]	
	},
	
	"camelRider":
	{
		"stackExperience" :
		[
			{
				"bonus" :
				{
					"subtype" : 0,
					"type" : "PRIMARY_SKILL"
				},
				"values" : [ 1, 1, 2, 2, 3, 3, 4, 4, 5, 5 ]
			},	
			{
				"bonus" :
				{
					"subtype" : 1,
					"type" : "PRIMARY_SKILL"
				},
				"values" : [ 1, 1, 2, 2, 3, 3, 4, 4, 5, 5 ]
			},
			{
				"bonus" :
				{
					"subtype" : 2,
					"type" : "CREATURE_DAMAGE"
				},
				"values" : [ 0, 1, 1, 2, 2, 3, 3, 4, 4, 5 ]
			},
			{
				"bonus" :
				{
					"subtype" : 1,
					"type" : "CREATURE_DAMAGE"
				},
				"values" : [ 0, 1, 1, 2, 2, 3, 3, 4, 4, 5 ]
			},
			{
				"bonus" :
				{
					"valueType" : "PERCENT_TO_BASE",
					"type" : "STACK_HEALTH"
				},
				"values" : [ 5, 10, 15, 20, 25, 30, 35, 40, 45, 50 ]
			},
			{
				"bonus" :
				{
					"type" : "STACKS_SPEED"
				},
				"values" : [ 0, 0, 0, 1, 1, 1, 1, 1, 1, 2 ]
			},
			{
				"bonus" :
				{
					"type" : "NO_TERRAIN_PENALTY",
					"subtype" : "terrain.sand",
					"propagator" : "HERO"
				},
				"values" : [ false, false, true, true, true, true, true, true, true, true ]
			}		
		]	
	},

	"desertWarrior":
	{
		"stackExperience" :
		[
			{
				"bonus" :
				{
					"subtype" : 0,
					"type" : "PRIMARY_SKILL"
				},
				"values" : [ 1, 1, 2, 2, 3, 3, 4, 4, 5, 5 ]
			},	
			{
				"bonus" :
				{
					"subtype" : 1,
					"type" : "PRIMARY_SKILL"
				},
				"values" : [ 1, 1, 2, 2, 3, 3, 4, 4, 5, 5 ]
			},
			{
				"bonus" :
				{
					"subtype" : 2,
					"type" : "CREATURE_DAMAGE"
				},
				"values" : [ 0, 1, 1, 2, 2, 3, 3, 4, 4, 5 ]
			},
			{
				"bonus" :
				{
					"subtype" : 1,
					"type" : "CREATURE_DAMAGE"
				},
				"values" : [ 0, 1, 1, 2, 2, 3, 3, 4, 4, 5 ]
			},
			{
				"bonus" :
				{
					"valueType" : "PERCENT_TO_BASE",
					"type" : "STACK_HEALTH"
				},
				"values" : [ 5, 10, 15, 20, 25, 30, 35, 40, 45, 50 ]
			},
			{
				"bonus" :
				{
					"type" : "STACKS_SPEED"
				},
				"values" : [ 0, 0, 0, 1, 1, 1, 1, 1, 1, 2 ]
			},
			{
				"bonus" :
				{
					"type" : "DOUBLE_DAMAGE_CHANCE"
				},
				"values" : [ 0, 0, 5, 5, 10, 10, 20, 20, 20, 30 ]
			}
		]	
	},

	"sekhmet":
	{
		"stackExperience" :
		[
			{
				"bonus" :
				{
					"subtype" : 0,
					"type" : "PRIMARY_SKILL"
				},
				"values" : [ 1, 2, 2, 3, 4, 5, 6, 6, 7, 8 ]
			},	
			{
				"bonus" :
				{
					"subtype" : 1,
					"type" : "PRIMARY_SKILL"
				},
				"values" : [ 1, 2, 2, 3, 4, 4, 5, 6, 7, 8 ]
			},
			{
				"bonus" :
				{
					"subtype" : 2,
					"type" : "CREATURE_DAMAGE"
				},
				"values" : [ 0, 1, 1, 2, 2, 3, 3, 4, 4, 5 ]
			},
			{
				"bonus" :
				{
					"subtype" : 1,
					"type" : "CREATURE_DAMAGE"
				},
				"values" : [ 0, 1, 1, 2, 2, 3, 3, 4, 4, 4 ]
			},
			{
				"bonus" :
				{
					"valueType" : "PERCENT_TO_BASE",
					"type" : "STACK_HEALTH"
				},
				"values" : [ 5, 10, 15, 20, 25, 30, 35, 40, 45, 50 ]
			},
			{
				"bonus" :
				{
					"type" : "STACKS_SPEED"
				},
				"values" : [ 0, 0, 0, 1, 1, 1, 1, 1, 1, 1 ]
			},
			{
				"bonus" :
				{
					"type" : "DIRECT_DAMAGE_IMMUNITY"
				},
				"values" : [ false, false, false, false, true, true, true, true, true, true ]
			},
			{
				"bonus" :
				{
					"type" : "SPELL_AFTER_ATTACK",
					"subtype" : 61, //"spell.forgetfulness",
					"addInfo" : [ 3, 2 ]
				},
				"values" : [ 5, 5, 10, 10, 10, 20, 20, 20, 25, 30 ]
			}
		]	
	},

	"sekhmetPriestess":
	{
		"stackExperience" :
		[
			{
				"bonus" :
				{
					"subtype" : 0,
					"type" : "PRIMARY_SKILL"
				},
				"values" : [ 1, 2, 2, 3, 4, 5, 6, 6, 7, 8 ]
			},	
			{
				"bonus" :
				{
					"subtype" : 1,
					"type" : "PRIMARY_SKILL"
				},
				"values" : [ 1, 2, 2, 3, 4, 4, 5, 6, 7, 8 ]
			},
			{
				"bonus" :
				{
					"subtype" : 2,
					"type" : "CREATURE_DAMAGE"
				},
				"values" : [ 0, 1, 1, 2, 2, 3, 3, 4, 4, 5 ]
			},
			{
				"bonus" :
				{
					"subtype" : 1,
					"type" : "CREATURE_DAMAGE"
				},
				"values" : [ 0, 1, 1, 2, 2, 3, 3, 4, 4, 4 ]
			},
			{
				"bonus" :
				{
					"valueType" : "PERCENT_TO_BASE",
					"type" : "STACK_HEALTH"
				},
				"values" : [ 5, 10, 15, 20, 25, 30, 35, 40, 45, 50 ]
			},
			{
				"bonus" :
				{
					"type" : "STACKS_SPEED"
				},
				"values" : [ 0, 0, 0, 1, 1, 1, 1, 1, 1, 2 ]
			},
			{
				"bonus" :
				{
					"type" : "DIRECT_DAMAGE_IMMUNITY"
				},
				"values" : [ false, false, false, false, false, false, false, false, true, true ]
			},
			{
				"bonus" :
				{
					"type" : "SPELL_AFTER_ATTACK",
					"subtype" : 61, //"spell.forgetfulness",
					"addInfo" : [ 3, 2 ]
				},
				"values" : [ 0, 5, 5, 10, 10, 10, 15, 15, 20, 20 ]
			},
			{
				"bonus" :
				{
					"type" : "SHOTS"
				},
				"values" : [ 0, 0, 0, 1, 1, 1, 1, 2, 2, 4 ]
			}
		]	
	},
	
	"ammut":
	{
		"stackExperience" :
		[
			{
				"bonus" :
				{
					"subtype" : 0,
					"type" : "PRIMARY_SKILL"
				},
				"values" : [ 1, 1, 2, 3, 4, 5, 5, 6, 7, 8 ]
			},	
			{
				"bonus" :
				{
					"subtype" : 1,
					"type" : "PRIMARY_SKILL"
				},
				"values" : [ 1, 2, 3, 3, 4, 4, 6, 6, 7, 8 ]
			},
			{
				"bonus" :
				{
					"subtype" : 2,
					"type" : "CREATURE_DAMAGE"
				},
				"values" : [ 1, 2, 2, 3, 4, 4, 5, 6, 7, 7 ]
			},
			{
				"bonus" :
				{
					"subtype" : 1,
					"type" : "CREATURE_DAMAGE"
				},
				"values" : [ 0, 1, 2, 3, 3, 4, 5, 6, 6, 7 ]
			},
			{
				"bonus" :
				{
					"valueType" : "PERCENT_TO_BASE",
					"type" : "STACK_HEALTH"
				},
				"values" : [ 5, 10, 15, 20, 25, 30, 35, 40, 45, 50 ]
			},
			{
				"bonus" :
				{
					"type" : "STACKS_SPEED"
				},
				"values" : [ 0, 0, 0, 1, 1, 1, 1, 1, 1, 1 ]
			},
			{
				"bonus" :
				{
					"type" : "JOUSTING"
				},
				"values" : [ false, false, false, false, true, true, true, true, true, true ]
			},	
			{
				"bonus" :
				{
					"type" : "ADDITIONAL_ATTACK"
				},
				"values" : [ 0, 0, 0, 0, 1, 1, 1, 1, 1, 1 ]
			}			
		]	
	},

	"sunAmmut":
	{
		"stackExperience" :
		[
			{
				"bonus" :
				{
					"subtype" : 0,
					"type" : "PRIMARY_SKILL"
				},
				"values" : [ 1, 1, 2, 3, 4, 5, 5, 6, 7, 8 ]
			},	
			{
				"bonus" :
				{
					"subtype" : 1,
					"type" : "PRIMARY_SKILL"
				},
				"values" : [ 1, 2, 3, 3, 4, 4, 6, 6, 7, 8 ]
			},
			{
				"bonus" :
				{
					"subtype" : 2,
					"type" : "CREATURE_DAMAGE"
				},
				"values" : [ 1, 2, 2, 3, 4, 4, 5, 6, 7, 7 ]
			},
			{
				"bonus" :
				{
					"subtype" : 1,
					"type" : "CREATURE_DAMAGE"
				},
				"values" : [ 0, 1, 2, 3, 3, 4, 5, 6, 6, 7 ]
			},
			{
				"bonus" :
				{
					"valueType" : "PERCENT_TO_BASE",
					"type" : "STACK_HEALTH"
				},
				"values" : [ 5, 10, 15, 20, 25, 30, 35, 40, 45, 50 ]
			},
			{
				"bonus" :
				{
					"type" : "STACKS_SPEED"
				},
				"values" : [ 0, 0, 0, 1, 1, 1, 1, 1, 1, 2 ]
			},
			{
				"bonus" :
				{
					"type" : "JOUSTING"
				},
				"values" : [ false, false, false, true, true, true, true, true, true, true ]
			},	
			{
				"bonus" :
				{
					"type" : "ADDITIONAL_ATTACK"
				},
				"values" : [ 0, 0, 0, 0, 0, 0, 0, 0, 1, 1 ]
			},
			{
				"bonus" :
				{
					"type" : "FEAR"
				},
				"values" : [ false, false, false, false, false, false, false, false, true, true ]
			}		
		]	
	},

	"sphinx":
	{
		"stackExperience" :
		[
			{
				"bonus" :
				{
					"subtype" : 0,
					"type" : "PRIMARY_SKILL"
				},
				"values" : [ 1, 2, 3, 4, 4, 5, 6, 7, 8, 9 ]
			},	
			{
				"bonus" :
				{
					"subtype" : 1,
					"type" : "PRIMARY_SKILL"
				},
				"values" : [ 1, 2, 2, 3, 4, 5, 6, 7, 8, 9 ]
			},
			{
				"bonus" :
				{
					"subtype" : 2,
					"type" : "CREATURE_DAMAGE"
				},
				"values" : [ 1, 2, 3, 4, 5, 6, 7, 8, 8, 9 ]
			},
			{
				"bonus" :
				{
					"subtype" : 1,
					"type" : "CREATURE_DAMAGE"
				},
				"values" : [ 0, 1, 2, 3, 4, 5, 5, 6, 7, 8 ]
			},
			{
				"bonus" :
				{
					"valueType" : "PERCENT_TO_BASE",
					"type" : "STACK_HEALTH"
				},
				"values" : [ 5, 10, 15, 20, 25, 30, 35, 40, 45, 50 ]
			},
			{
				"bonus" :
				{
					"type" : "STACKS_SPEED"
				},
				"values" : [ 0, 0, 0, 1, 1, 1, 1, 1, 1, 2 ]
			},
			{
				"bonus" :
				{
					"type" : "TWO_HEX_ATTACK_BREATH"
				},
				"values" : [ false, false, false, false, true, true, true, true, true, true ]
			},
			{
				"bonus" :
				{
					"type" : "MAGIC_RESISTANCE"
				},
				"values" : [ 20, 20, 25, 30, 30, 35, 35, 40, 45, 50 ]
			}			
		]	
	},

	"elderSphinx":
	{
		"stackExperience" :
		[
			{
				"bonus" :
				{
					"subtype" : 0,
					"type" : "PRIMARY_SKILL"
				},
				"values" : [ 1, 2, 3, 4, 4, 5, 6, 7, 8, 9 ]
			},	
			{
				"bonus" :
				{
					"subtype" : 1,
					"type" : "PRIMARY_SKILL"
				},
				"values" : [ 1, 2, 2, 3, 4, 5, 6, 7, 8, 9 ]
			},
			{
				"bonus" :
				{
					"subtype" : 2,
					"type" : "CREATURE_DAMAGE"
				},
				"values" : [ 1, 2, 3, 4, 5, 6, 7, 8, 8, 9 ]
			},
			{
				"bonus" :
				{
					"subtype" : 1,
					"type" : "CREATURE_DAMAGE"
				},
				"values" : [ 0, 1, 2, 3, 4, 5, 5, 6, 7, 8 ]
			},
			{
				"bonus" :
				{
					"valueType" : "PERCENT_TO_BASE",
					"type" : "STACK_HEALTH"
				},
				"values" : [ 5, 10, 15, 20, 25, 30, 35, 40, 45, 50 ]
			},
			{
				"bonus" :
				{
					"type" : "STACKS_SPEED"
				},
				"values" : [ 0, 0, 0, 1, 1, 1, 1, 1, 1, 2 ]
			},
			{
				"bonus" :
				{
					"type" : "TWO_HEX_ATTACK_BREATH"
				},
				"values" : [ false, false, false, false, false, false, false, true, true, true ]
			},
			{
				"bonus" :
				{
					"type" : "MAGIC_RESISTANCE"
				},
				"values" : [ 40, 40, 45, 50, 50, 50, 50, 55, 55, 60 ]
			}
		]	
	},

	"anubis":
	{
		"stackExperience" :
		[
			{
				"bonus" :
				{
					"subtype" : 0,
					"type" : "PRIMARY_SKILL"
				},
				"values" : [ 1, 2, 3, 4, 5, 6, 7, 8, 9, 10 ]
			},	
			{
				"bonus" :
				{
					"subtype" : 1,
					"type" : "PRIMARY_SKILL"
				},
				"values" : [ 1, 2, 3, 4, 5, 6, 7, 8, 9, 10 ]
			},
			{
				"bonus" :
				{
					"subtype" : 2,
					"type" : "CREATURE_DAMAGE"
				},
				"values" : [ 1, 2, 3, 4, 5, 6, 7, 8, 9, 10 ]
			},
			{
				"bonus" :
				{
					"subtype" : 1,
					"type" : "CREATURE_DAMAGE"
				},
				"values" : [ 1, 2, 3, 4, 5, 6, 7, 8, 9, 10 ]
			},
			{
				"bonus" :
				{
					"valueType" : "PERCENT_TO_BASE",
					"type" : "STACK_HEALTH"
				},
				"values" : [ 5, 10, 15, 20, 25, 30, 35, 40, 45, 50 ]
			},
			{
				"bonus" :
				{
					"type" : "STACKS_SPEED"
				},
				"values" : [ 0, 0, 0, 0, 1, 1, 2, 2, 3, 3 ]
			},
			{
				"bonus" :
				{
					"type" : "MANA_CHANNELING"
				},
				"values" : [ 0, 5, 5, 10, 10, 20, 20, 30, 30, 40 ]
			},
			{
				"bonus" :
				{
					"type" : "ENCHANTED",
					"subtype" : 28 //"spell.airShield"
				},
				"values" : [ 1, 1, 1, 2, 2, 2, 2, 3, 3, 3 ]
			},
			{
				"bonus" :
				{
					"type" : "CHANGES_SPELL_COST_FOR_ENEMY"
				},
				"values" : [ 0, 1, 1, 1, 1, 1, 2, 2, 2, 3 ]
			}
		]	
	},

	"anubisWarrior":
	{
		"stackExperience" :
		[
			{
				"bonus" :
				{
					"subtype" : 0,
					"type" : "PRIMARY_SKILL"
				},
				"values" : [ 1, 2, 3, 4, 5, 6, 7, 8, 9, 10 ]
			},	
			{
				"bonus" :
				{
					"subtype" : 1,
					"type" : "PRIMARY_SKILL"
				},
				"values" : [ 1, 2, 3, 4, 5, 6, 7, 8, 9, 10 ]
			},
			{
				"bonus" :
				{
					"subtype" : 2,
					"type" : "CREATURE_DAMAGE"
				},
				"values" : [ 1, 2, 3, 4, 5, 6, 7, 8, 9, 10 ]
			},
			{
				"bonus" :
				{
					"subtype" : 1,
					"type" : "CREATURE_DAMAGE"
				},
				"values" : [ 1, 2, 3, 4, 5, 6, 7, 8, 9, 10 ]
			},
			{
				"bonus" :
				{
					"valueType" : "PERCENT_TO_BASE",
					"type" : "STACK_HEALTH"
				},
				"values" : [ 5, 10, 15, 20, 25, 30, 35, 40, 45, 50 ]
			},
			{
				"bonus" :
				{
					"type" : "STACKS_SPEED"
				},
				"values" : [ 0, 0, 0, 0, 1, 1, 2, 2, 3, 4 ]
			},
			{
				"bonus" :
				{
					"type" : "MANA_DRAIN"
				},
				"values" : [ 0, 0, 1, 2, 3, 3, 4, 5, 5, 6 ]
			},
			{
				"bonus" :
				{
					"type" : "ENCHANTED",
					"subtype" : 28 //"spell.airShield"
				},
				"values" : [ 0, 0, 1, 1, 1, 2, 2, 2, 3, 3 ]
			},
			{
				"bonus" :
				{
					"type" : "CHANGES_SPELL_COST_FOR_ENEMY"
				},
				"values" : [ 0, 0, 1, 1, 1, 1, 1, 2, 2, 3 ]
			}			
		]	
	},
	
	"scarab":
	{
		"stackExperience" :
		[
			{	
				"bonus" :
				{
					"subtype" : 0,
					"type" : "PRIMARY_SKILL"
				},
				"values" : [ 0, 1, 1, 1, 1, 2, 2, 2, 2, 3 ]
			},	
			{
				"bonus" :
				{
					"subtype" : 1,
					"type" : "PRIMARY_SKILL"
				},
				"values" : [ 1, 1, 1, 1, 2, 2, 2, 2, 3, 3 ]
			},
			{
				"bonus" :
				{
					"subtype" : 2,
					"type" : "CREATURE_DAMAGE"
				},
				"values" : [ 0, 0, 1, 1, 1, 1, 2, 2, 2, 2 ]
			},
			{
				"bonus" :
				{
					"subtype" : 1,
					"type" : "CREATURE_DAMAGE"
				},
				"values" : [ 0, 0, 0, 1, 1, 1, 1, 2, 2, 2 ]
			},
			{
				"bonus" :
				{
					"valueType" : "PERCENT_TO_BASE",
					"type" : "STACK_HEALTH"
				},
				"values" : [ 5, 10, 15, 20, 25, 30, 35, 40, 45, 50 ]
			},
			{
				"bonus" :
				{
					"type" : "STACKS_SPEED"
				},
				"values" : [ 0, 0, 0, 1, 1, 1, 1, 1, 2, 2 ]
			},
			{
				"bonus" :
				{
					"type" : "LUCK"
				},
				"values" : [ 1, 1, 1, 2, 2, 2, 2, 2, 3, 3 ]
			},
			{
				"bonus" :
				{
					"type" : "FIRE_SHIELD"
				},
				"values" : [ false, false, false, true, true, true, true, true, true, true ]
			}			
		]	
	}
}
